soccer/main.py
soccer_mcp_server-0.1.0.dist-info/METADATA
soccer_mcp_server-0.1.0.dist-info/WHEEL
soccer_mcp_server-0.1.0.dist-info/entry_points.txt
soccer_mcp_server-0.1.0.dist-info/top_level.txt
soccer_mcp_server-0.1.0.dist-info/RECORD
