Metadata-Version: 2.4
Name: soccer-mcp-server
Version: 0.1.0
Summary: Add your description here
Requires-Python: >=3.11
Requires-Dist: langchain>=0.3.21
Requires-Dist: langgraph>=0.3.20
Requires-Dist: mcp[cli]>=1.5.0
Requires-Dist: pandas>=2.2.3
Requires-Dist: pydantic>=2.10.6
